{"products":[{"image":"http://dummyimage.com/179x100.png/dddddd/000000","name":"Bananas","tag":"Sumberkemuning","price":"$995.22","store":"Ronstring"},
{"image":"http://dummyimage.com/213x100.png/5fa2dd/ffffff","name":"Buttons","tag":"Saint Louis","price":"$257.03","store":"Tres-Zap"},
{"image":"http://dummyimage.com/193x100.png/dddddd/000000","name":"Chicken Breast Halal","tag":"Santana do Paraíso","price":"$383.97","store":"Konklab"},
{"image":"http://dummyimage.com/236x100.png/dddddd/000000","name":"Tart Shells - Savory, 4","tag":"Hecheng","price":"$444.64","store":"Quo Lux"},
{"image":"http://dummyimage.com/100x100.png/cc0000/ffffff","name":"Chocolate Liqueur - Godet White","tag":"Argotirto Krajan","price":"$108.20","store":"Regrant"},
{"image":"http://dummyimage.com/175x100.png/cc0000/ffffff","name":"Pastry - Lemon Danish - Mini","tag":"Zhuxing Chaoxianzu","price":"$914.77","store":"Quo Lux"},
{"image":"http://dummyimage.com/204x100.png/5fa2dd/ffffff","name":"Bread Base - Gold Formel","tag":"Lapuan","price":"$347.01","store":"Voltsillam"},
{"image":"http://dummyimage.com/209x100.png/dddddd/000000","name":"Bowl 12 Oz - Showcase 92012","tag":"Obock","price":"$419.95","store":"Latlux"},
{"image":"http://dummyimage.com/150x100.png/5fa2dd/ffffff","name":"Spice - Peppercorn Melange","tag":"Handaqi","price":"$457.52","store":"Holdlamis"},
{"image":"http://dummyimage.com/112x100.png/ff4444/ffffff","name":"Vinegar - White Wine","tag":"Criciúma","price":"$820.40","store":"Duobam"},
{"image":"http://dummyimage.com/138x100.png/5fa2dd/ffffff","name":"Cheese - Augre Des Champs","tag":"Lukovo","price":"$311.77","store":"Subin"},
{"image":"http://dummyimage.com/213x100.png/cc0000/ffffff","name":"Bay Leaf","tag":"Dawuhan","price":"$326.34","store":"Flexidy"},
{"image":"http://dummyimage.com/155x100.png/dddddd/000000","name":"Longos - Grilled Salmon With Bbq","tag":"Zolotyy Potik","price":"$554.62","store":"Fixflex"},
{"image":"http://dummyimage.com/102x100.png/cc0000/ffffff","name":"Butter Balls Salted","tag":"Sebewe","price":"$459.51","store":"Overhold"},
{"image":"http://dummyimage.com/187x100.png/5fa2dd/ffffff","name":"Cup - 4oz Translucent","tag":"Savalou","price":"$660.65","store":"Domainer"},
{"image":"http://dummyimage.com/130x100.png/5fa2dd/ffffff","name":"Pork - Loin, Boneless","tag":"Sogcho","price":"$715.41","store":"Alphazap"},
{"image":"http://dummyimage.com/174x100.png/cc0000/ffffff","name":"Clam - Cherrystone","tag":"Asamboka","price":"$901.13","store":"Zathin"},
{"image":"http://dummyimage.com/127x100.png/dddddd/000000","name":"Allspice - Jamaican","tag":"Maslovka","price":"$389.21","store":"Zontrax"},
{"image":"http://dummyimage.com/214x100.png/dddddd/000000","name":"Tomatoes - Hot House","tag":"Xingong","price":"$867.82","store":"Ronstring"},
{"image":"http://dummyimage.com/193x100.png/cc0000/ffffff","name":"Flour - Pastry","tag":"Tangba","price":"$311.40","store":"Flexidy"},
{"image":"http://dummyimage.com/121x100.png/dddddd/000000","name":"Kolrabi","tag":"Canggou","price":"$947.66","store":"Prodder"},
{"image":"http://dummyimage.com/239x100.png/5fa2dd/ffffff","name":"Seabream Whole Farmed","tag":"Illéla","price":"$639.82","store":"Solarbreeze"},
{"image":"http://dummyimage.com/140x100.png/ff4444/ffffff","name":"Lettuce - California Mix","tag":"Shedok","price":"$560.02","store":"Sonair"},
{"image":"http://dummyimage.com/216x100.png/ff4444/ffffff","name":"Goat - Leg","tag":"Beizhuang","price":"$134.49","store":"Aerified"},
{"image":"http://dummyimage.com/188x100.png/dddddd/000000","name":"Island Oasis - Pina Colada","tag":"Brazzaville","price":"$434.82","store":"Konklab"},
{"image":"http://dummyimage.com/124x100.png/5fa2dd/ffffff","name":"Container - Clear 16 Oz","tag":"Pa Tio","price":"$431.13","store":"Flowdesk"},
{"image":"http://dummyimage.com/170x100.png/dddddd/000000","name":"Veal - Heart","tag":"Archis","price":"$668.44","store":"Voyatouch"},
{"image":"http://dummyimage.com/105x100.png/5fa2dd/ffffff","name":"Cheese - Parmesan Cubes","tag":"Malaya Purga","price":"$522.35","store":"Ventosanzap"},
{"image":"http://dummyimage.com/179x100.png/dddddd/000000","name":"Bonito Flakes - Toku Katsuo","tag":"Álimos","price":"$915.55","store":"Alpha"},
{"image":"http://dummyimage.com/176x100.png/ff4444/ffffff","name":"Praline Paste","tag":"Kunri","price":"$587.83","store":"Flexidy"},
{"image":"http://dummyimage.com/165x100.png/cc0000/ffffff","name":"Turkey - Breast, Boneless Sk On","tag":"Norabats’","price":"$338.94","store":"Domainer"},
{"image":"http://dummyimage.com/183x100.png/cc0000/ffffff","name":"Soup - Base Broth Beef","tag":"Xujiahe","price":"$222.55","store":"Bamity"},
{"image":"http://dummyimage.com/100x100.png/ff4444/ffffff","name":"Mushroom - Shitake, Fresh","tag":"Loma Alta","price":"$826.70","store":"Zoolab"},
{"image":"http://dummyimage.com/110x100.png/5fa2dd/ffffff","name":"Nut - Pecan, Halves","tag":"Ferapontovo","price":"$935.14","store":"Flexidy"},
{"image":"http://dummyimage.com/182x100.png/5fa2dd/ffffff","name":"Cheese - Shred Cheddar / Mozza","tag":"Kalmar","price":"$887.36","store":"Y-Solowarm"},
{"image":"http://dummyimage.com/157x100.png/ff4444/ffffff","name":"Pepper - Paprika, Spanish","tag":"Augsburg","price":"$434.88","store":"Cardify"},
{"image":"http://dummyimage.com/178x100.png/5fa2dd/ffffff","name":"Wine - Lou Black Shiraz","tag":"L'Île-Perrot","price":"$587.76","store":"Biodex"},
{"image":"http://dummyimage.com/167x100.png/cc0000/ffffff","name":"Juice - Clamato, 341 Ml","tag":"São José de Mipibu","price":"$197.34","store":"Stronghold"},
{"image":"http://dummyimage.com/197x100.png/cc0000/ffffff","name":"Eel - Smoked","tag":"Nakhon Pathom","price":"$363.83","store":"Konklux"},
{"image":"http://dummyimage.com/113x100.png/ff4444/ffffff","name":"Crab - Soft Shell","tag":"Yunhe","price":"$209.84","store":"Vagram"},
{"image":"http://dummyimage.com/232x100.png/cc0000/ffffff","name":"Wine - Ej Gallo Sonoma","tag":"Taiping","price":"$540.79","store":"Zathin"},
{"image":"http://dummyimage.com/210x100.png/cc0000/ffffff","name":"Butter - Pod","tag":"Anwen","price":"$550.88","store":"Zaam-Dox"},
{"image":"http://dummyimage.com/195x100.png/cc0000/ffffff","name":"Water - Evian 355 Ml","tag":"Uchaly","price":"$223.46","store":"Domainer"},
{"image":"http://dummyimage.com/145x100.png/5fa2dd/ffffff","name":"Ecolab - Ster Bac","tag":"Affery","price":"$189.26","store":"Alpha"},
{"image":"http://dummyimage.com/181x100.png/5fa2dd/ffffff","name":"Syrup - Monin - Granny Smith","tag":"La Esperanza","price":"$184.05","store":"Sonsing"},
{"image":"http://dummyimage.com/190x100.png/dddddd/000000","name":"Beef - Bones, Cut - Up","tag":"Qintang","price":"$799.37","store":"Namfix"},
{"image":"http://dummyimage.com/188x100.png/5fa2dd/ffffff","name":"Pork - Bacon Cooked Slcd","tag":"Jaleswar","price":"$489.96","store":"Quo Lux"},
{"image":"http://dummyimage.com/198x100.png/ff4444/ffffff","name":"Papadam","tag":"New Yekepa","price":"$619.40","store":"Holdlamis"},
{"image":"http://dummyimage.com/134x100.png/5fa2dd/ffffff","name":"Nut - Walnut, Pieces","tag":"Phoenix","price":"$194.17","store":"Voyatouch"},
{"image":"http://dummyimage.com/238x100.png/5fa2dd/ffffff","name":"Wine - Bourgogne 2002, La","tag":"Hwange","price":"$198.84","store":"Gembucket"},
{"image":"http://dummyimage.com/242x100.png/5fa2dd/ffffff","name":"Cognac - Courvaisier","tag":"Unisław","price":"$284.96","store":"Quo Lux"},
{"image":"http://dummyimage.com/216x100.png/ff4444/ffffff","name":"Tea Peppermint","tag":"Englewood","price":"$951.47","store":"Transcof"},
{"image":"http://dummyimage.com/240x100.png/5fa2dd/ffffff","name":"Taro Root","tag":"Porsgrunn","price":"$988.12","store":"Sonair"},
{"image":"http://dummyimage.com/141x100.png/cc0000/ffffff","name":"Ecolab - Balanced Fusion","tag":"Resende","price":"$510.92","store":"Otcom"},
{"image":"http://dummyimage.com/215x100.png/5fa2dd/ffffff","name":"Rice - Basmati","tag":"Sukawaris","price":"$450.90","store":"Flowdesk"},
{"image":"http://dummyimage.com/224x100.png/5fa2dd/ffffff","name":"Wine - Zonnebloem Pinotage","tag":"Huntsville","price":"$343.22","store":"Aerified"},
{"image":"http://dummyimage.com/176x100.png/5fa2dd/ffffff","name":"Nacho Chips","tag":"Barra Cheia","price":"$258.07","store":"Solarbreeze"},
{"image":"http://dummyimage.com/227x100.png/5fa2dd/ffffff","name":"Lid - 10,12,16 Oz","tag":"Panjāb","price":"$794.86","store":"Bitwolf"},
{"image":"http://dummyimage.com/161x100.png/5fa2dd/ffffff","name":"Flour - Bread","tag":"Ołpiny","price":"$240.47","store":"Lotstring"},
{"image":"http://dummyimage.com/170x100.png/cc0000/ffffff","name":"Bread - Ciabatta Buns","tag":"Béboto","price":"$270.01","store":"Kanlam"},
{"image":"http://dummyimage.com/149x100.png/cc0000/ffffff","name":"Beef - Ground Medium","tag":"Tangcun","price":"$260.54","store":"Tin"},
{"image":"http://dummyimage.com/214x100.png/5fa2dd/ffffff","name":"Flour - Pastry","tag":"Thị Trấn Mộc Châu","price":"$662.84","store":"Flowdesk"},
{"image":"http://dummyimage.com/240x100.png/dddddd/000000","name":"Carroway Seed","tag":"Hualingang","price":"$608.40","store":"Regrant"},
{"image":"http://dummyimage.com/241x100.png/5fa2dd/ffffff","name":"Spice - Greek 1 Step","tag":"Banepa","price":"$744.71","store":"Daltfresh"},
{"image":"http://dummyimage.com/134x100.png/cc0000/ffffff","name":"Flounder - Fresh","tag":"Tabonok","price":"$843.07","store":"Pannier"},
{"image":"http://dummyimage.com/183x100.png/ff4444/ffffff","name":"Pineapple - Canned, Rings","tag":"Żyraków","price":"$522.35","store":"Konklab"},
{"image":"http://dummyimage.com/145x100.png/5fa2dd/ffffff","name":"Cheese - Goat","tag":"Soca","price":"$180.21","store":"Cookley"},
{"image":"http://dummyimage.com/174x100.png/dddddd/000000","name":"Fish - Soup Base, Bouillon","tag":"Bandundu","price":"$356.81","store":"Overhold"},
{"image":"http://dummyimage.com/234x100.png/5fa2dd/ffffff","name":"Flower - Dish Garden","tag":"Nueva Loja","price":"$968.21","store":"Tampflex"},
{"image":"http://dummyimage.com/195x100.png/ff4444/ffffff","name":"Bandage - Flexible Neon","tag":"Bagumbayan","price":"$562.24","store":"Greenlam"},
{"image":"http://dummyimage.com/200x100.png/5fa2dd/ffffff","name":"Soup - Knorr, Chicken Noodle","tag":"Mahaddayweyne","price":"$738.75","store":"Transcof"},
{"image":"http://dummyimage.com/231x100.png/ff4444/ffffff","name":"Cake - French Pear Tart","tag":"Marieville","price":"$491.48","store":"Fix San"},
{"image":"http://dummyimage.com/215x100.png/dddddd/000000","name":"Bread - Hot Dog Buns","tag":"Klampis","price":"$705.24","store":"Overhold"},
{"image":"http://dummyimage.com/130x100.png/cc0000/ffffff","name":"Bread - Kimel Stick Poly","tag":"Anjepy","price":"$947.96","store":"Daltfresh"},
{"image":"http://dummyimage.com/176x100.png/dddddd/000000","name":"Nantucket - Carrot Orange","tag":"Château-Richer","price":"$871.79","store":"Zaam-Dox"},
{"image":"http://dummyimage.com/138x100.png/ff4444/ffffff","name":"Wine - Casablanca Valley","tag":"Nehe","price":"$153.01","store":"Fintone"},
{"image":"http://dummyimage.com/217x100.png/cc0000/ffffff","name":"Melon - Watermelon Yellow","tag":"Aracaju","price":"$889.37","store":"Holdlamis"},
{"image":"http://dummyimage.com/247x100.png/5fa2dd/ffffff","name":"Duck - Legs","tag":"Karangbungur","price":"$701.73","store":"Mat Lam Tam"},
{"image":"http://dummyimage.com/131x100.png/dddddd/000000","name":"Duck - Whole","tag":"Kalabahi","price":"$234.94","store":"Voltsillam"},
{"image":"http://dummyimage.com/234x100.png/ff4444/ffffff","name":"Beer - Molson Excel","tag":"Rossosh’","price":"$139.58","store":"Rank"},
{"image":"http://dummyimage.com/236x100.png/cc0000/ffffff","name":"Breadfruit","tag":"Longtan","price":"$648.24","store":"Bamity"},
{"image":"http://dummyimage.com/250x100.png/dddddd/000000","name":"Pepper - Black, Whole","tag":"Bāglung","price":"$153.71","store":"Toughjoyfax"},
{"image":"http://dummyimage.com/244x100.png/cc0000/ffffff","name":"Cookie Dough - Oatmeal Rasin","tag":"Akureyri","price":"$121.74","store":"Flexidy"},
{"image":"http://dummyimage.com/212x100.png/ff4444/ffffff","name":"Soup - Campbells","tag":"Buritizeiro","price":"$645.13","store":"Bitwolf"},
{"image":"http://dummyimage.com/132x100.png/cc0000/ffffff","name":"Blackberries","tag":"Champerico","price":"$885.64","store":"Mat Lam Tam"},
{"image":"http://dummyimage.com/189x100.png/5fa2dd/ffffff","name":"Water - Green Tea Refresher","tag":"Ōmuta","price":"$915.10","store":"Fixflex"},
{"image":"http://dummyimage.com/150x100.png/ff4444/ffffff","name":"Monkfish Fresh - Skin Off","tag":"Cibeureum","price":"$692.17","store":"Y-find"},
{"image":"http://dummyimage.com/129x100.png/5fa2dd/ffffff","name":"Beef - Tenderloin","tag":"Pandat","price":"$842.30","store":"Rank"},
{"image":"http://dummyimage.com/100x100.png/5fa2dd/ffffff","name":"Coffee - Ristretto Coffee Capsule","tag":"Ntungamo","price":"$310.21","store":"Span"},
{"image":"http://dummyimage.com/189x100.png/cc0000/ffffff","name":"Lamb Rack Frenched Australian","tag":"Fukuma","price":"$645.49","store":"Alpha"},
{"image":"http://dummyimage.com/141x100.png/dddddd/000000","name":"Cake - Sheet Strawberry","tag":"Orléans","price":"$788.63","store":"Zamit"},
{"image":"http://dummyimage.com/156x100.png/ff4444/ffffff","name":"Tea Leaves - Oolong","tag":"Khashuri","price":"$773.41","store":"Namfix"},
{"image":"http://dummyimage.com/133x100.png/5fa2dd/ffffff","name":"Clams - Canned","tag":"Banjar Medura","price":"$960.49","store":"Bitchip"},
{"image":"http://dummyimage.com/166x100.png/5fa2dd/ffffff","name":"Oil - Grapeseed Oil","tag":"Kuching","price":"$408.78","store":"Regrant"},
{"image":"http://dummyimage.com/211x100.png/ff4444/ffffff","name":"Beef Ground Medium","tag":"Vršac","price":"$411.80","store":"Flowdesk"},
{"image":"http://dummyimage.com/140x100.png/dddddd/000000","name":"Flower - Commercial Spider","tag":"Verrettes","price":"$581.13","store":"Zontrax"},
{"image":"http://dummyimage.com/198x100.png/cc0000/ffffff","name":"Ham - Cooked Bayonne Tinned","tag":"Picoto","price":"$610.75","store":"Alpha"},
{"image":"http://dummyimage.com/216x100.png/ff4444/ffffff","name":"Nescafe - Frothy French Vanilla","tag":"Tokmok","price":"$887.90","store":"Pannier"},
{"image":"http://dummyimage.com/110x100.png/cc0000/ffffff","name":"Onions - Red","tag":"Balaka","price":"$567.77","store":"Asoka"},
{"image":"http://dummyimage.com/217x100.png/ff4444/ffffff","name":"Tomato Paste","tag":"San Manuel","price":"$853.94","store":"Fintone"}]}